bluing/__init__.py
bluing/__main__.py
bluing/common.py
bluing/gap_data.py
bluing/ui.py
bluing/android/__init__.py
bluing/android/__main__.py
bluing/android/btsnooz.py
bluing/android/collect_btsnoop_log.py
bluing/android/ui.py
bluing/br/__init__.py
bluing/br/__main__.py
bluing/br/br_scan.py
bluing/br/lmp.py
bluing/br/sdp_scan.py
bluing/br/ui.py
bluing/le/__init__.py
bluing/le/__main__.py
bluing/le/gatt_scan.py
bluing/le/gatt_scan_bt_agent.py
bluing/le/le_scan.py
bluing/le/ll.py
bluing/le/microbit.py
bluing/le/serial_protocol.py
bluing/le/ui.py
bluing/le/res/__init__.py
bluing/plugin/__init__.py
bluing/plugin/__main__.py
bluing/plugin/exception.py
bluing/plugin/plugin.py
bluing/plugin/ui.py
bluing/plugin/install/__init__.py
bluing/plugin/install/__main__.py
bluing/plugin/install/ui.py
bluing/plugin/list/__init__.py
bluing/plugin/list/__main__.py
bluing/plugin/list/ui.py
bluing/plugin/run/__init__.py
bluing/plugin/run/__main__.py
bluing/plugin/run/ui.py
bluing/plugin/uninstall/__init__.py
bluing/plugin/uninstall/__main__.py
bluing/plugin/uninstall/ui.py
bluing/res/CompanyIdentfiers.csv
bluing/res/gatt-characteristic-uuid.txt
bluing/res/gatt-declaration-uuid.txt
bluing/res/gatt-descriptor-uuid.txt
bluing/res/gatt-service-uuid.txt
bluing/res/micro-bit.hex
bluing/res/oui.txt
bluing/res/sdp_ProfileDescriptorList_protocol_ids.txt
bluing/res/service-class-profile-ids.txt
bluing/service_record/__init__.py
bluing/service_record/ag_service_record.py
bluing/service_record/hf_service_record.py
bluing/service_record/hid_service_record.py
bluing/service_record/mce_service_record.py
bluing/service_record/mse_service_record.py
bluing/service_record/op_service_record.py
bluing/spoof/__init__.py
bluing/spoof/__main__.py
bluing/spoof/ui.py
bluing-0.12.0.dist-info/LICENSE.txt
bluing-0.12.0.dist-info/METADATA
bluing-0.12.0.dist-info/WHEEL
bluing-0.12.0.dist-info/entry_points.txt
bluing-0.12.0.dist-info/top_level.txt
bluing-0.12.0.dist-info/RECORD
