Metadata-Version: 2.1
Name: bluing
Version: 0.12.0
Summary: An intelligence gathering tool for hacking Bluetooth
Home-page: https://github.com/fO-000/bluing
Author: Sourcell Xu
Author-email: sourcell.xu@outlook.com
Classifier: Operating System :: POSIX :: Linux
Classifier: Environment :: Console
Classifier: Programming Language :: Python :: 3
Classifier: Programming Language :: Python :: 3 :: Only
Classifier: Programming Language :: Python :: 3.10
Classifier: Topic :: Security
Classifier: Topic :: System :: Networking
Classifier: Topic :: System :: Hardware :: Universal Serial Bus (USB) :: Wireless Controller
Classifier: Intended Audience :: Developers
Classifier: Intended Audience :: Education
Classifier: Intended Audience :: Information Technology
Classifier: Intended Audience :: Science/Research
Classifier: Intended Audience :: System Administrators
Classifier: Intended Audience :: Telecommunications Industry
Classifier: License :: OSI Approved :: GNU General Public License v3 or later (GPLv3+)
Requires-Python: ==3.10.*
License-File: LICENSE.txt
Requires-Dist: PyGObject (>=3.42.2)
Requires-Dist: bluepy (>=1.3.0)
Requires-Dist: btatt (>=0.0.19)
Requires-Dist: btgatt (>=0.0.22)
Requires-Dist: bthci (>=0.0.44)
Requires-Dist: btsm (>=0.0.16)
Requires-Dist: dbus-python (>=1.3.2)
Requires-Dist: docopt (>=0.6.2)
Requires-Dist: halo (>=0.0.31)
Requires-Dist: pyserial (>=3.5)
Requires-Dist: xpycommon (>=0.0.25)
